{"attributes":[{"children":[{"children":[{"children":[{"children":null,"text":"Gramene taxonomy ID","description":null,"name":"gramene_taxonomy_id","model_reference":null,"display_name":"Gramene taxonomy ID","default":false,"id":"pg9gakm8","leaf":true},{"children":null,"text":"Germplasm name ","description":null,"name":"germplasm_name","model_reference":null,"display_name":"Germplasm name ","default":false,"id":"knu6i3jb","leaf":true},{"children":null,"text":"Common name","description":null,"name":"common_name","model_reference":null,"display_name":"Common name","default":false,"id":"xxwqlx40","leaf":true},{"children":null,"text":"Species","description":null,"name":"species","model_reference":null,"display_name":"Species","default":false,"id":"nj1jle1o","leaf":true},{"children":null,"text":"Cmap species accession ","description":null,"name":"cmap_species_accession","model_reference":null,"display_name":"Cmap species accession ","default":false,"id":"ijdpp8co","leaf":true},{"children":null,"text":"Ncbi taxonomy ID","description":null,"name":"ncbi_taxonomy_id","model_reference":null,"display_name":"Ncbi taxonomy ID","default":false,"id":"sd7isf8x","leaf":true}],"text":"Species","name":"species","max_select":null,"display_name":"Species","id":"9l4pcy55","leaf":false},{"children":[{"children":null,"text":"Library name","description":null,"name":"library_name","model_reference":null,"display_name":"Library name","default":false,"id":"m2g0ebs9","leaf":true}],"text":"Library","name":"library","max_select":null,"display_name":"Library","id":"fr6ukiet","leaf":false},{"children":[{"children":null,"text":"Marker name","description":null,"name":"marker_name","model_reference":null,"display_name":"Marker name","default":false,"id":"wqkvegz9","leaf":true},{"children":null,"text":"Marker description","description":null,"name":"marker_desc","model_reference":null,"display_name":"Marker description","default":false,"id":"2tumvb8j","leaf":true},{"children":null,"text":"Marker version","description":null,"name":"version","model_reference":null,"display_name":"Marker version","default":false,"id":"kn1n8i16","leaf":true},{"children":null,"text":"Synonym name","description":null,"name":"marker_synonym","model_reference":null,"display_name":"Synonym name","default":false,"id":"hh2dssez","leaf":true},{"children":null,"text":"Synonym description","description":null,"name":"synonym_desc","model_reference":null,"display_name":"Synonym description","default":false,"id":"i6f91d6w","leaf":true}],"text":"Marker","name":"marker","max_select":null,"display_name":"Marker","id":"b9knogll","leaf":false},{"children":[{"children":null,"text":"Analysis type","description":null,"name":"analysis_type","model_reference":null,"display_name":"Analysis type","default":false,"id":"lo6grv98","leaf":true},{"children":null,"text":"Analysis name","description":null,"name":"analysis_name","model_reference":null,"display_name":"Analysis name","default":false,"id":"os1fq8xh","leaf":true}],"text":"Analysis","name":"analysis_to_marker","max_select":null,"display_name":"Analysis","id":"vrjwchjz","leaf":false},{"children":[{"children":null,"text":"Marker name","description":null,"name":"ac_marker_name","model_reference":null,"display_name":"Marker name","default":false,"id":"13f4zwyj","leaf":true},{"children":null,"text":"Analytical correspondence type","description":null,"name":"ac_type","model_reference":null,"display_name":"Analytical correspondence type","default":false,"id":"1t72m5tw","leaf":true},{"children":null,"text":"Analysis name","description":null,"name":"ac_analysis_name","model_reference":null,"display_name":"Analysis name","default":false,"id":"zg38woch","leaf":true},{"children":null,"text":"Marker accession","description":null,"name":"ac_marker_acc","model_reference":null,"display_name":"Marker accession","default":false,"id":"no9q7ysz","leaf":true},{"children":null,"text":"Marker version","description":null,"name":"ac_marker_version","model_reference":null,"display_name":"Marker version","default":false,"id":"nv3rsh6w","leaf":true},{"children":null,"text":"Marker type","description":null,"name":"ac_marker_type","model_reference":null,"display_name":"Marker type","default":false,"id":"mpjg6dg6","leaf":true}],"text":"Analytical correspondence","name":"analytical_correspondence","max_select":null,"display_name":"Analytical correspondence","id":"hfjs18n7","leaf":false}],"text":"Markers","name":"markers","max_select":null,"display_name":"Markers","id":"m899bg3t","leaf":false},{"children":[{"children":[{"children":null,"text":"Biological Process acc","description":null,"name":"biologicalprocess","model_reference":null,"display_name":"Biological Process acc","default":false,"id":"u2lf58yo","leaf":true},{"children":null,"text":"Cellular Component acc","description":null,"name":"cellularcomponent","model_reference":null,"display_name":"Cellular Component acc","default":false,"id":"33frnpzd","leaf":true},{"children":null,"text":"Environment acc","description":null,"name":"environment","model_reference":null,"display_name":"Environment acc","default":false,"id":"f9i91qab","leaf":true},{"children":null,"text":"Growth Stage acc","description":null,"name":"growthstage","model_reference":null,"display_name":"Growth Stage acc","default":false,"id":"z7xagenz","leaf":true},{"children":null,"text":"Molecular Function acc","description":null,"name":"molecularfunction","model_reference":null,"display_name":"Molecular Function acc","default":false,"id":"e5n5mg0e","leaf":true},{"children":null,"text":"Plant Growth acc","description":null,"name":"plantgrowth","model_reference":null,"display_name":"Plant Growth acc","default":false,"id":"k0vcyoo","leaf":true},{"children":null,"text":"Plant Structure acc","description":null,"name":"plantstructure","model_reference":null,"display_name":"Plant Structure acc","default":false,"id":"sksceypd","leaf":true},{"children":null,"text":"Trait acc","description":null,"name":"trait","model_reference":null,"display_name":"Trait acc","default":false,"id":"el2cf1f6","leaf":true}],"text":"Ontology","name":"ontology","max_select":null,"display_name":"Ontology","id":"7gpu9wc1","leaf":false}],"text":"Ontology","name":"ontology","max_select":null,"display_name":"Ontology","id":"n80s19zf","leaf":false},{"children":[{"children":[{"children":null,"text":"Gramene Literature","description":null,"name":"xref_grameneliterature","model_reference":null,"display_name":"Gramene Literature","default":false,"id":"k09jzulz","leaf":true},{"children":null,"text":"NCBI GEOGPL2025 Affymetrix","description":null,"name":"xref_ncbigeogpl2025affymetrix","model_reference":null,"display_name":"NCBI GEOGPL2025 Affymetrix","default":false,"id":"jw7fxzlw","leaf":true},{"children":null,"text":"Agilent Rice","description":null,"name":"xref_agilentrice","model_reference":null,"display_name":"Agilent Rice","default":false,"id":"y5xo65gf","leaf":true},{"children":null,"text":"Grain Genes","description":null,"name":"xref_graingenes","model_reference":null,"display_name":"Grain Genes","default":false,"id":"7iz8bezv","leaf":true},{"children":null,"text":"NCBI GEOGPL892 Agilent 012106","description":null,"name":"xref_ncbigeogpl892agilent012106","model_reference":null,"display_name":"NCBI GEOGPL892 Agilent 012106","default":false,"id":"dl29r7i2","leaf":true},{"children":null,"text":"TGICGI","description":null,"name":"xref_tgicgi","model_reference":null,"display_name":"TGICGI","default":false,"id":"pxverfdy","leaf":true},{"children":null,"text":"TGIAQGI","description":null,"name":"xref_tgiaqgi","model_reference":null,"display_name":"TGIAQGI","default":false,"id":"kosi5buj","leaf":true},{"children":null,"text":"TGIBNGI","description":null,"name":"xref_tgibngi","model_reference":null,"display_name":"TGIBNGI","default":false,"id":"b1dmvdvy","leaf":true},{"children":null,"text":"TGIBVGI","description":null,"name":"xref_tgibvgi","model_reference":null,"display_name":"TGIBVGI","default":false,"id":"m1y6eab4","leaf":true},{"children":null,"text":"TGICAGI","description":null,"name":"xref_tgicagi","model_reference":null,"display_name":"TGICAGI","default":false,"id":"i4jgkt4a","leaf":true},{"children":null,"text":"TGICHRGI","description":null,"name":"xref_tgichrgi","model_reference":null,"display_name":"TGICHRGI","default":false,"id":"76woqcx2","leaf":true},{"children":null,"text":"TGIFAGI","description":null,"name":"xref_tgifagi","model_reference":null,"display_name":"TGIFAGI","default":false,"id":"cyd8tw5a","leaf":true},{"children":null,"text":"TGIGMGI","description":null,"name":"xref_tgigmgi","model_reference":null,"display_name":"TGIGMGI","default":false,"id":"kswj0bul","leaf":true},{"children":null,"text":"TGIHAGI","description":null,"name":"xref_tgihagi","model_reference":null,"display_name":"TGIHAGI","default":false,"id":"g40f8en5","leaf":true},{"children":null,"text":"TGIHVGI","description":null,"name":"xref_tgihvgi","model_reference":null,"display_name":"TGIHVGI","default":false,"id":"dshhglns","leaf":true},{"children":null,"text":"TGILJGI","description":null,"name":"xref_tgiljgi","model_reference":null,"display_name":"TGILJGI","default":false,"id":"ogd72plb","leaf":true},{"children":null,"text":"TGILSGI","description":null,"name":"xref_tgilsgi","model_reference":null,"display_name":"TGILSGI","default":false,"id":"c2zx8qhq","leaf":true},{"children":null,"text":"TGIMCGI","description":null,"name":"xref_tgimcgi","model_reference":null,"display_name":"TGIMCGI","default":false,"id":"tnrusjjm","leaf":true},{"children":null,"text":"TGIMTGI","description":null,"name":"xref_tgimtgi","model_reference":null,"display_name":"TGIMTGI","default":false,"id":"1a9n2wvm","leaf":true},{"children":null,"text":"TGINTGI","description":null,"name":"xref_tgintgi","model_reference":null,"display_name":"TGINTGI","default":false,"id":"tgufd2s0","leaf":true},{"children":null,"text":"TGINBGI","description":null,"name":"xref_tginbgi","model_reference":null,"display_name":"TGINBGI","default":false,"id":"curb1uge","leaf":true},{"children":null,"text":"TGIOGI","description":null,"name":"xref_tgiogi","model_reference":null,"display_name":"TGIOGI","default":false,"id":"hd0zu9lo","leaf":true},{"children":null,"text":"TGIONGI","description":null,"name":"xref_tgiongi","model_reference":null,"display_name":"TGIONGI","default":false,"id":"pn1knth","leaf":true},{"children":null,"text":"TGIAGI","description":null,"name":"xref_tgiagi","model_reference":null,"display_name":"TGIAGI","default":false,"id":"ict4vyuq","leaf":true},{"children":null,"text":"TGIPPLGI","description":null,"name":"xref_tgipplgi","model_reference":null,"display_name":"TGIPPLGI","default":false,"id":"89umjdy9","leaf":true},{"children":null,"text":"TGIPHVGI","description":null,"name":"xref_tgiphvgi","model_reference":null,"display_name":"TGIPHVGI","default":false,"id":"iinerkw3","leaf":true},{"children":null,"text":"TGIRYEGI","description":null,"name":"xref_tgiryegi","model_reference":null,"display_name":"TGIRYEGI","default":false,"id":"iwz441fr","leaf":true},{"children":null,"text":"TGISBGI","description":null,"name":"xref_tgisbgi","model_reference":null,"display_name":"TGISBGI","default":false,"id":"mtdnhp5r","leaf":true},{"children":null,"text":"TGISOGI","description":null,"name":"xref_tgisogi","model_reference":null,"display_name":"TGISOGI","default":false,"id":"ccem67eb","leaf":true},{"children":null,"text":"TGISTGI","description":null,"name":"xref_tgistgi","model_reference":null,"display_name":"TGISTGI","default":false,"id":"jei9bwok","leaf":true},{"children":null,"text":"TGITAGI","description":null,"name":"xref_tgitagi","model_reference":null,"display_name":"TGITAGI","default":false,"id":"c4odhxkm","leaf":true},{"children":null,"text":"TGITCAGI","description":null,"name":"xref_tgitcagi","model_reference":null,"display_name":"TGITCAGI","default":false,"id":"u36vlao0","leaf":true},{"children":null,"text":"TGITVERGI","description":null,"name":"xref_tgitvergi","model_reference":null,"display_name":"TGITVERGI","default":false,"id":"1b7c3ujj","leaf":true},{"children":null,"text":"TGIZMGI","description":null,"name":"xref_tgizmgi","model_reference":null,"display_name":"TGIZMGI","default":false,"id":"uab2rmw0","leaf":true},{"children":null,"text":"TGIVVGI","description":null,"name":"xref_tgivvgi","model_reference":null,"display_name":"TGIVVGI","default":false,"id":"bpoaht9g","leaf":true},{"children":null,"text":"PubMed","description":null,"name":"xref_pubmed","model_reference":null,"display_name":"PubMed","default":false,"id":"u8mlabd3","leaf":true}],"text":"Xrefs","name":"xrefs","max_select":null,"display_name":"Xrefs","id":"n99ytztl","leaf":false}],"text":"Xrefs","name":"xrefs","max_select":null,"display_name":"Xrefs","id":"b1fcdwh0","leaf":false},{"children":[{"children":[{"children":null,"text":"Cell line ","description":null,"name":"cell_line_108","model_reference":null,"display_name":"Cell line ","default":false,"id":"yipgpps4","leaf":true},{"children":null,"text":"Cell type","description":null,"name":"cell_type_108","model_reference":null,"display_name":"Cell type","default":false,"id":"l8prvwqh","leaf":true},{"children":null,"text":"Center name","description":null,"name":"center_name","model_reference":null,"display_name":"Center name","default":false,"id":"7xbzfhrc","leaf":true},{"children":null,"text":"Center project","description":null,"name":"center_project","model_reference":null,"display_name":"Center project","default":false,"id":"x7fqsot5","leaf":true},{"children":null,"text":"Development stage ","description":null,"name":"development_stage","model_reference":null,"display_name":"Development stage ","default":false,"id":"2tnb0a3k","leaf":true},{"children":null,"text":"EO term ","description":null,"name":"eo_term","model_reference":null,"display_name":"EO term ","default":false,"id":"ybb7d3n4","leaf":true},{"children":null,"text":"Gro term","description":null,"name":"gro_term","model_reference":null,"display_name":"Gro term","default":false,"id":"zh0vseb6","leaf":true},{"children":null,"text":"MD5 sum","description":null,"name":"md5_sum","model_reference":null,"display_name":"MD5 sum","default":false,"id":"lvdhlnzz","leaf":true},{"children":null,"text":"PO term ","description":null,"name":"po_term","model_reference":null,"display_name":"PO term ","default":false,"id":"1z0jg30d","leaf":true},{"children":null,"text":"Seq","description":null,"name":"seq","model_reference":null,"display_name":"Seq","default":false,"id":"66tp2sup","leaf":true},{"children":null,"text":"Seq length ","description":null,"name":"seq_length","model_reference":null,"display_name":"Seq length ","default":false,"id":"oqubpc97","leaf":true}],"text":"RFLP","name":"marker","max_select":null,"display_name":"RFLP","id":"37erzc8m","leaf":false}],"text":"RFLP","name":"extras","max_select":null,"display_name":"RFLP","id":"lslqdts3","leaf":false}],"text":"Markers","name":"markers","max_select":null,"display_name":"Markers","formatters":"html,txt,csv,tsv,xls","id":"1qs8s9ow","leaf":false}],"filters":[{"children":[{"children":[{"children":[{"children":null,"text":"Species","description":null,"qualifier":"like","name":"species","options":null,"model_reference":null,"display_name":"Species","default":false,"id":"5s7pnv5l","leaf":true}],"text":"Species","name":"species","display_name":"Species","id":"kzf864oi","leaf":false},{"children":[{"children":null,"text":"Common name ","description":null,"qualifier":"like","name":"common_name","options":null,"model_reference":null,"display_name":"Common name ","default":false,"id":"kf2z4bxj","leaf":true}],"text":"Common name","name":"cn","display_name":"Common name","id":"bsqs6lc5","leaf":false},{"children":[{"children":null,"text":"Taxonomy Term ID(s) (e.g. GR_tax:013681)","description":null,"qualifier":"like","name":"term_accession_101","options":null,"model_reference":null,"display_name":"Taxonomy Term ID(s) (e.g. GR_tax:013681)","default":false,"id":"8paz1thy","leaf":true},{"children":null,"text":"Taxonomy Term ID(s) incl. Ancestors","description":null,"qualifier":"like","name":"term_accession_102","options":null,"model_reference":null,"display_name":"Taxonomy Term ID(s) incl. Ancestors","default":false,"id":"ss2ny4yb","leaf":true},{"children":null,"text":"Taxonomy Term ID(s) incl. Descendants","description":null,"qualifier":"like","name":"term_accession_103","options":null,"model_reference":null,"display_name":"Taxonomy Term ID(s) incl. Descendants","default":false,"id":"nqqdilwf","leaf":true},{"children":null,"text":"Taxonomy Term ID(s) incl. Parents","description":null,"qualifier":"like","name":"term_accession_104","options":null,"model_reference":null,"display_name":"Taxonomy Term ID(s) incl. Parents","default":false,"id":"kbsnlz98","leaf":true},{"children":null,"text":"Taxonomy Term ID(s) incl. Children","description":null,"qualifier":"like","name":"term_accession_105","options":null,"model_reference":null,"display_name":"Taxonomy Term ID(s) incl. Children","default":false,"id":"c5is6z2u","leaf":true},{"children":null,"text":"Taxonomy Term Name(s) (e.g. Oryza)","description":null,"qualifier":"=","name":"term_name_101","options":null,"model_reference":null,"display_name":"Taxonomy Term Name(s) (e.g. Oryza)","default":false,"id":"tgluun8q","leaf":true},{"children":null,"text":"Taxonomy Term Name(s) incl. Ancestors","description":null,"qualifier":"=","name":"term_name_102","options":null,"model_reference":null,"display_name":"Taxonomy Term Name(s) incl. Ancestors","default":false,"id":"dndvozyt","leaf":true},{"children":null,"text":"Taxonomy Term Name(s) incl. Descendants","description":null,"qualifier":"=","name":"term_name_103","options":null,"model_reference":null,"display_name":"Taxonomy Term Name(s) incl. Descendants","default":false,"id":"7svf1fa2","leaf":true},{"children":null,"text":"Taxonomy Term Name(s) incl. Parents","description":null,"qualifier":"=","name":"term_name_104","options":null,"model_reference":null,"display_name":"Taxonomy Term Name(s) incl. Parents","default":false,"id":"ipulf3yf","leaf":true},{"children":null,"text":"Taxonomy Term Name(s) incl. Children","description":null,"qualifier":"=","name":"term_name_105","options":null,"model_reference":null,"display_name":"Taxonomy Term Name(s) incl. Children","default":false,"id":"igf9vrxl","leaf":true}],"text":"Gramene taxonomy","name":"gramene","display_name":"Gramene taxonomy","id":"cowd0unw","leaf":false},{"children":[{"children":null,"text":"NCBI taxonomy ID","description":null,"qualifier":"like","name":"ncbi_taxonomy_id","options":null,"model_reference":null,"display_name":"NCBI taxonomy ID","default":false,"id":"uhq7xxxt","leaf":true}],"text":"NCBI taxonomy","name":"ncbi","display_name":"NCBI taxonomy","id":"hd8qz7i5","leaf":false}],"text":"Species","name":"species","display_name":"Species","id":"75r3j8wp","leaf":false},{"children":[{"children":[{"children":null,"text":"Library name","description":null,"qualifier":"=","name":"library_name","options":"Mlu1 Targeted Wheat BAC Library,UNKNOWN,Zea mays cv. B73 RFLP","model_reference":null,"display_name":"Library name","default":false,"id":"axya9pgt","leaf":true}],"text":"Library","name":"library","display_name":"Library","id":"vg9wq1yi","leaf":false},{"children":[{"children":null,"text":"Germplasm name","description":null,"qualifier":"like","name":"germplasm_name","options":null,"model_reference":null,"display_name":"Germplasm name","default":false,"id":"dirs6wux","leaf":true}],"text":"Germplasm","name":"germplasm","display_name":"Germplasm","id":"1nn5boea","leaf":false},{"children":[{"children":null,"text":"Marker name(s) only","description":null,"qualifier":"like","name":"marker_name","options":null,"model_reference":null,"display_name":"Marker name(s) only","default":false,"id":"1y78c6f8","leaf":true},{"children":null,"text":"Marker name(s) including synonyms","description":null,"qualifier":"like","name":"synonym_name","options":null,"model_reference":null,"display_name":"Marker name(s) including synonyms","default":false,"id":"7ybzsqvg","leaf":true}],"text":"Marker or synonym name","name":"marker_name","display_name":"Marker or synonym name","id":"hqrrl8d6","leaf":false},{"children":[{"children":null,"text":"Synonym type ","description":null,"qualifier":"=","name":"synonym_type","options":"GRAINGENES_GENE,GRAINGENES_PROBE,MAIZEGDB_PROBE,SUCEST,UNKNOWN","model_reference":null,"display_name":"Synonym type ","default":false,"id":"qsnt6wj9","leaf":true}],"text":"Synonym type","name":"synonymtype","display_name":"Synonym type","id":"asy0io6h","leaf":false},{"children":[{"children":null,"text":"Synonym count >=","description":null,"qualifier":">=","name":"synonym_count","options":null,"model_reference":null,"display_name":"Synonym count >=","default":false,"id":"lf9p1i3z","leaf":true}],"text":"Synonym count >=","name":"syncount","display_name":"Synonym count >=","id":"zga6qs24","leaf":false},{"children":[{"children":null,"text":"Analytical correspondence type","description":null,"qualifier":"=","name":"acorr_type","options":"entrez,FTP download,overgo_file","model_reference":null,"display_name":"Analytical correspondence type","default":false,"id":"l3gch983","leaf":true},{"children":null,"text":"Analytical correspondence marker type","description":null,"qualifier":"like","name":"acorr_marker_type","options":null,"model_reference":null,"display_name":"Analytical correspondence marker type","default":false,"id":"sz991952","leaf":true}],"text":"Analytical correspondence type","name":"acorr_type","display_name":"Analytical correspondence type","id":"4tqxq3dy","leaf":false},{"children":[{"children":null,"text":"Analytical correspondence marker name","description":null,"qualifier":"like","name":"acorr_marker_name","options":null,"model_reference":null,"display_name":"Analytical correspondence marker name","default":false,"id":"m9m1s9vh","leaf":true}],"text":"Analytical correspondence marker","name":"acorr_marker","display_name":"Analytical correspondence marker","id":"e4tzvvlt","leaf":false}],"text":"Marker","name":"marker","display_name":"Marker","id":"q9af04zl","leaf":false}],"text":"Marker","name":"naive_filters","display_name":"Marker","id":"wcd527k5","leaf":false}]}